[
  {
    "id": "1",
    "buyerId": "1",
    "productId": "1",
    "startTime": "2017-09-08T19:01:45.714942+03:00",
    "endTime": "2017-09-08T19:01:55.714942+03:00"
  },
  {
    "id": "2",
    "buyerId": "2",
    "productId": "2",
    "startTime": "2017-09-08T19:01:45.714942+03:00",
    "endTime": "2017-09-08T19:01:55.714942+03:00"
  },
  {
    "id": "3",
    "buyerId": "3",
    "productId": "3",
    "startTime": "2017-09-08T19:01:45.714942+03:00",
    "endTime": "2017-09-08T19:01:55.714942+03:00"
  },
  {
    "id": "4",
    "buyerId": "1",
    "productId": "4",
    "startTime": "2017-09-08T19:01:45.714942+03:00",
    "endTime": "2017-09-08T19:01:55.714942+03:00"
  }
]